CONTRIBUTING.md
LICENSE
MANIFEST.in
Makefile
README.md
pyproject.toml
setup.py
docs/Makefile
docs/make.bat
docs/source/conf.py
docs/source/index.md
pynixconfig/__init__.py
pynixconfig/linuxconfig.py
pynixconfig.egg-info/PKG-INFO
pynixconfig.egg-info/SOURCES.txt
pynixconfig.egg-info/dependency_links.txt
pynixconfig.egg-info/requires.txt
pynixconfig.egg-info/top_level.txt
pynixconfig/tests/test_all.py