Metadata-Version: 2.1
Name: pynixconfig
Version: 0.1.1
Summary: Simple way to config your terminal colors
Author-email: Sergio Nahas <sn2865@columbia.edu>
License: MIT License
Project-URL: repository, https://github.com/sn2865/pynixconfig
Platform: UNKNOWN
Classifier: Development Status :: 2 - Pre-Alpha
Classifier: Programming Language :: Python :: Implementation :: CPython
Classifier: Programming Language :: Python :: Implementation :: PyPy
Classifier: Programming Language :: Python :: 3
Classifier: Programming Language :: Python :: 3.7
Classifier: Programming Language :: Python :: 3.8
Classifier: Programming Language :: Python :: 3.9
Classifier: Programming Language :: Python :: 3.10
Classifier: Programming Language :: Python :: 3.11
Requires-Python: >=3.7
Provides-Extra: develop
License-File: LICENSE
